{"summaries":[{"symbol":{"__symbol":0},"metadata":{"__symbolic":"class","statics":{"logger":{"__symbolic":"call","expression":{"__symbolic":"select","expression":{"__symbol":1},"member":"makeLogger"},"arguments":[{"__symbol":0}]}}},"type":{"summaryKind":3,"type":{"reference":{"__symbol":0},"diDeps":[{"isAttribute":false,"isHost":false,"isSelf":false,"isSkipSelf":false,"isOptional":false,"token":{"identifier":{"reference":{"__symbol":2}}}}],"lifecycleHooks":[]}}}],"symbols":[{"__symbol":0,"name":"PostMessageBridgeImpl","filePath":"/Users/obrian/projects/angular2-post-message/src/PostMessageBridgeImpl.d.ts"},{"__symbol":1,"name":"LoggerFactory","filePath":"/Users/obrian/projects/angular2-post-message/node_modules/ts-smart-logger/index.d.ts"},{"__symbol":2,"name":"NgZone","filePath":"/Users/obrian/projects/angular2-post-message/node_modules/@angular/core/src/zone/ng_zone.d.ts"}]}